INSTALL.md
LICENSE
MANIFEST.in
README.md
pyproject.toml
setup.py
aimv2_json_alchemy.egg-info/PKG-INFO
aimv2_json_alchemy.egg-info/SOURCES.txt
aimv2_json_alchemy.egg-info/dependency_links.txt
aimv2_json_alchemy.egg-info/top_level.txt
json_alchemy/__init__.py
json_alchemy/_json_alchemy.c
json_alchemy/include/json_flattener.h
json_alchemy/include/json_schema_generator.h
json_alchemy/include/json_utils.h
json_alchemy/include/thread_pool.h
json_alchemy/include/cjson/cJSON.h
json_alchemy/src/cJSON.c
json_alchemy/src/json_flattener.c
json_alchemy/src/json_schema_generator.c
json_alchemy/src/json_tools.c
json_alchemy/src/json_utils.c
json_alchemy/src/thread_pool.c
tests/test_json_alchemy.py